<?xml version="1.0" encoding="UTF-8" standalone="no"?>
<objects>
  <object>
    <ID>0</ID>
    <name>drop</name>
    <type>DROP</type>
    <value>-1</value>
    <items>-1</items>
    <description>A reward dropped by the monster you just killed.</description>
  </object>
  <object>
    <ID>231321</ID>
    <name>table</name>
    <type>FURNITURE</type>
    <value>-1</value>
    <items>-1</items>
    <description>A table.</description>
  </object>
  <object>
    <ID>321323</ID>
    <name>chest</name>
    <type>CHEST</type>
    <value>-1</value>
    <items>0</items>
    <description>A chest that contains loot.</description>
  </object>
  <object>
    <ID>231211</ID>
    <name>chair</name>
    <type>FURNITURE</type>
    <value>-1</value>
    <items>-1</items>
    <description>A wooden chair.</description>
  </object>
  <object>
    <ID>232112</ID>
    <name>bench</name>
    <type>FURNITURE</type>
    <value>-1</value>
    <items>-1</items>
    <description>A wooden bench.</description>
  </object>
  <object>
    <ID>231113</ID>
    <name>cauldron</name>
    <type>FURNITURE</type>
    <value>-1</value>
    <items>-1</items>
    <description>An iron cauldron.</description>
  </object>
</objects>
